foliant/preprocessors/flags.py
foliantcontrib.flags-1.0.1.dist-info/DESCRIPTION.rst
foliantcontrib.flags-1.0.1.dist-info/METADATA
foliantcontrib.flags-1.0.1.dist-info/RECORD
foliantcontrib.flags-1.0.1.dist-info/WHEEL
foliantcontrib.flags-1.0.1.dist-info/metadata.json
foliantcontrib.flags-1.0.1.dist-info/top_level.txt
