Metadata-Version: 2.0
Name: foliantcontrib.flags
Version: 1.0.1
Summary: Conditional content block inclusion for Foliant.
Home-page: https://github.com/foliant-docs/foliantcontrib
Author: Konstantin Molchanov
Author-email: moigagoo@live.com
License: MIT
Platform: any
Classifier: Development Status :: 5 - Production/Stable
Classifier: Environment :: Console
Classifier: Intended Audience :: Developers
Classifier: License :: OSI Approved :: MIT License
Classifier: Operating System :: OS Independent
Classifier: Programming Language :: Python
Classifier: Topic :: Documentation
Classifier: Topic :: Utilities
Requires-Dist: foliant (>=1.0.0)
